cycleplotter/__init__.py
cycleplotter/main.py
cycleplotter/entities/__init__.py
cycleplotter/entities/cycle_duration.py
cycleplotter/infrastructure/__init__.py
cycleplotter/infrastructure/files/__init__.py
cycleplotter/infrastructure/files/opener.py
cycleplotter/interfaceadapters/__init__.py
cycleplotter/interfaceadapters/config.py
cycleplotter/interfaceadapters/cli/__init__.py
cycleplotter/interfaceadapters/cli/argparser.py
cycleplotter/interfaceadapters/cycledataparser/__init__.py
cycleplotter/interfaceadapters/cycledataparser/applehealth.py
cycleplotter/interfaceadapters/cycledataparser/factory.py
cycleplotter/interfaceadapters/cycledataparser/withingshealthmate.py
cycleplotter/usecases/__init__.py
cycleplotter/usecases/cycle_dates_to_durations.py
cycleplotter/usecases/extract_cycle_durations.py
cycleplotter/usecases/cycledataparser/__init__.py
cycleplotter/usecases/cycledataparser/base.py
cycleplotter/usecases/plotter/__init__.py
cycleplotter/usecases/plotter/config.py
cycleplotter/usecases/plotter/plot_cycle_durations.py
cycle_plotter-0.0.1rc2.dist-info/LICENSE
cycle_plotter-0.0.1rc2.dist-info/METADATA
cycle_plotter-0.0.1rc2.dist-info/WHEEL
cycle_plotter-0.0.1rc2.dist-info/entry_points.txt
cycle_plotter-0.0.1rc2.dist-info/top_level.txt
cycle_plotter-0.0.1rc2.dist-info/RECORD
