Metadata-Version: 2.1
Name: cycle-plotter
Version: 0.0.1rc2
Summary: Command line tool to plot a graph of cycles exported from Apple Health or Withings Health Mate.
Author-email: Carmen Alvarez <carmen@rmen.ca>
License: MIT License
Project-URL: Repository, https://github.com/caarmen/cycle-plotter
Project-URL: Changelog, https://github.com/caarmen/cycle-plotter/releases
Keywords: cli,health
Classifier: Development Status :: 3 - Alpha
Classifier: Environment :: Console
Classifier: Framework :: Matplotlib
Classifier: Intended Audience :: End Users/Desktop
Classifier: License :: OSI Approved :: MIT License
Classifier: Programming Language :: Python :: 3
Requires-Python: >=3.11
License-File: LICENSE
Requires-Dist: defusedxml
Requires-Dist: matplotlib
